AUTHORS
ChangeLog
LICENSE
README.rst
requirements.txt
setup.cfg
setup.py
plato_clean/__init__.py
plato_clean/cmd.py
plato_clean.egg-info/PKG-INFO
plato_clean.egg-info/SOURCES.txt
plato_clean.egg-info/dependency_links.txt
plato_clean.egg-info/entry_points.txt
plato_clean.egg-info/not-zip-safe
plato_clean.egg-info/pbr.json
plato_clean.egg-info/requires.txt
plato_clean.egg-info/top_level.txt
plato_clean/alerts/__init__.py
plato_clean/alerts/console.py
plato_clean/alerts/onealert.py
plato_clean/alerts/slack.py
plato_clean/alerts/sms.py
plato_clean/cases/__init__.py
plato_clean/cases/eip.py
plato_clean/cases/image.py
plato_clean/cases/instance.py
plato_clean/cases/key_pair.py
plato_clean/cases/load_balancer.py
plato_clean/cases/network.py
plato_clean/cases/snapshot.py
plato_clean/cases/volume.py
plato_clean/sdk/__init__.py
plato_clean/sdk/codes.py
plato_clean/sdk/conn.py
plato_clean/sdk/errors.py
plato_clean/sdk/regions.py
plato_clean/sdk/actions/__init__.py
plato_clean/sdk/actions/api.py
plato_clean/sdk/actions/instances.py
plato_clean/sdk/actions/networks.py
plato_clean/sdk/actions/params.py
plato_clean/sdk/actions/volumes.py